setup.cfg
setup.py
autopxd/__init__.py
autopxd.egg-info/PKG-INFO
autopxd.egg-info/SOURCES.txt
autopxd.egg-info/dependency_links.txt
autopxd.egg-info/entry_points.txt
autopxd.egg-info/requires.txt
autopxd.egg-info/top_level.txt
autopxd/include/_ansi.h
autopxd/include/_fake_defines.h
autopxd/include/_fake_typedefs.h
autopxd/include/_syslist.h
autopxd/include/alloca.h
autopxd/include/ar.h
autopxd/include/argz.h
autopxd/include/assert.h
autopxd/include/complex.h
autopxd/include/ctype.h
autopxd/include/dirent.h
autopxd/include/dlfcn.h
autopxd/include/endian.h
autopxd/include/envz.h
autopxd/include/errno.h
autopxd/include/fastmath.h
autopxd/include/fcntl.h
autopxd/include/features.h
autopxd/include/fenv.h
autopxd/include/float.h
autopxd/include/getopt.h
autopxd/include/grp.h
autopxd/include/iconv.h
autopxd/include/ieeefp.h
autopxd/include/inttypes.h
autopxd/include/iso646.h
autopxd/include/langinfo.h
autopxd/include/libgen.h
autopxd/include/libintl.h
autopxd/include/limits.h
autopxd/include/locale.h
autopxd/include/malloc.h
autopxd/include/math.h
autopxd/include/netdb.h
autopxd/include/newlib.h
autopxd/include/paths.h
autopxd/include/process.h
autopxd/include/pthread.h
autopxd/include/pwd.h
autopxd/include/reent.h
autopxd/include/regdef.h
autopxd/include/regex.h
autopxd/include/sched.h
autopxd/include/search.h
autopxd/include/semaphore.h
autopxd/include/setjmp.h
autopxd/include/signal.h
autopxd/include/stdarg.h
autopxd/include/stdbool.h
autopxd/include/stddef.h
autopxd/include/stdint.h
autopxd/include/stdio.h
autopxd/include/stdlib.h
autopxd/include/string.h
autopxd/include/syslog.h
autopxd/include/tar.h
autopxd/include/termios.h
autopxd/include/tgmath.h
autopxd/include/time.h
autopxd/include/unctrl.h
autopxd/include/unistd.h
autopxd/include/utime.h
autopxd/include/utmp.h
autopxd/include/wchar.h
autopxd/include/wctype.h
autopxd/include/zlib.h
autopxd/include/arpa/inet.h
autopxd/include/asm-generic/int-ll64.h
autopxd/include/linux/socket.h
autopxd/include/linux/version.h
autopxd/include/netinet/in.h
autopxd/include/netinet/tcp.h
autopxd/include/openssl/err.h
autopxd/include/openssl/evp.h
autopxd/include/openssl/hmac.h
autopxd/include/openssl/ssl.h
