Metadata-Version: 1.1
Name: autopxd
Version: 1.0.0
Summary: Automatically generate Cython pxd files from C headers
Home-page: http://github.com/tarruda/autopxd
Author: Thiago de Arruda
Author-email: tpadilha84@gmail.com
License: MIT
Download-URL: http://github.com/tarruda/autopxd/archive/1.0.0.tar.gz
Platform: UNKNOWN
